bandit_plugins/__init__.py
bandit_plugins/allow_selected_modules.py
bandit_allowed_modules-0.0.1.dist-info/AUTHORS
bandit_allowed_modules-0.0.1.dist-info/METADATA
bandit_allowed_modules-0.0.1.dist-info/WHEEL
bandit_allowed_modules-0.0.1.dist-info/entry_points.txt
bandit_allowed_modules-0.0.1.dist-info/top_level.txt
bandit_allowed_modules-0.0.1.dist-info/RECORD
